popo_fsm.py
setup.py
popo_fsm.egg-info/PKG-INFO
popo_fsm.egg-info/SOURCES.txt
popo_fsm.egg-info/dependency_links.txt
popo_fsm.egg-info/requires.txt
popo_fsm.egg-info/top_level.txt