Metadata-Version: 1.1
Name: popo-fsm
Version: 0.0.2
Summary: Plain old python object finite state machine support.
Home-page: https://github.com/redpandalabs/popo-fsm
Author: Red Panda Innovation Labs
Author-email: nitish@redpanda.co.in
License: MIT License
Platform: UNKNOWN
Classifier: Development Status :: 4 - Beta
Classifier: Intended Audience :: Developers
Classifier: License :: OSI Approved :: MIT License
Classifier: Operating System :: OS Independent
Classifier: Programming Language :: Python
